transformers_helper/__init__.py
transformers_helper/models/__init__.py
transformers_helper/models/ann/__init__.py
transformers_helper/models/ann/configuration_ann.py
transformers_helper/models/ann/feature_extraction_ann.py
transformers_helper/models/ann/modeling_ann.py
transformers_helper/models/cnn/__init__.py
transformers_helper/models/cnn/configuration_cnn.py
transformers_helper/models/cnn/image_processing_cnn.py
transformers_helper/models/cnn/modeling_cnn.py
transformers_helper/models/custom_bert/__init__.py
transformers_helper/models/custom_bert/configuration_custom_bert.py
transformers_helper/models/custom_bert/modeling_custom_bert.py
transformers_helper/models/custom_wav2vec2/__init__.py
transformers_helper/models/custom_wav2vec2/feature_extraction_custom_wav2vec2.py
transformers_helper/models/embedded_1dcnn/__init__.py
transformers_helper/models/embedded_1dcnn/configuration_embedded_1dcnn.py
transformers_helper/models/embedded_1dcnn/modeling_embedded_1dcnn.py
transformers_helper/models/embedded_rnn/__init__.py
transformers_helper/models/embedded_rnn/configuration_embedded_rnn.py
transformers_helper/models/embedded_rnn/modeling_embedded_rnn.py
transformers_helper/models/embedded_rnn/tokenization_embedded_rnn.py
transformers_helper/models/faster_rcnn/__init__.py
transformers_helper/models/faster_rcnn/configuration_faster_rcnn.py
transformers_helper/models/faster_rcnn/image_processing_faster_rcnn.py
transformers_helper/models/faster_rcnn/modeling_faster_rcnn.py
transformers_helper/models/rnn/__init__.py
transformers_helper/models/rnn/configuration_rnn.py
transformers_helper/models/rnn/modeling_rnn.py
transformers_helper/pipelines/__init__.py
transformers_helper/pipelines/custom_image_classification_pipeline.py
transformers_helper/pipelines/fixed_length_translation_pipeline.py
transformers_helper/pipelines/tabular_binary_classification_pipeline.py
transformers_helper/pipelines/tabular_classification_pipeline.py
transformers_helper-0.0.7.dist-info/METADATA
transformers_helper-0.0.7.dist-info/WHEEL
transformers_helper-0.0.7.dist-info/top_level.txt
transformers_helper-0.0.7.dist-info/RECORD
