Metadata-Version: 2.1
Name: transformers-helper
Version: 0.0.7
Summary: Transformers helper
Home-page: https://github.com/automatethem/transformers-helper
Author: Sang Ki Kwon
Author-email: automatethem@gmail.com
License: MIT
Platform: UNKNOWN
Requires-Dist: transformers
Requires-Dist: pytorch-helper
Requires-Dist: torchtext
Requires-Dist: konlpy
